versuchung/__init__.py
versuchung/__main__.py
versuchung/archives.py
versuchung/database.py
versuchung/events.py
versuchung/execute.py
versuchung/experiment.py
versuchung/files.py
versuchung/jupyter.py
versuchung/search.py
versuchung/tex.py
versuchung/tools.py
versuchung/types.py
versuchung-1.4.2.dist-info/COPYING
versuchung-1.4.2.dist-info/METADATA
versuchung-1.4.2.dist-info/WHEEL
versuchung-1.4.2.dist-info/top_level.txt
versuchung-1.4.2.dist-info/RECORD
