Metadata-Version: 2.1
Name: versuchung
Version: 1.4.2
Summary: A toolbox for experiments
Home-page: http://github.de/stettberger/versuchung
Author: Christian Dietrich
Author-email: stettberger@dokucode.de
License: GPLv3
Classifier: Development Status :: 4 - Beta
Classifier: Environment :: Console
Classifier: Intended Audience :: Science/Research
Classifier: License :: OSI Approved :: GNU General Public License v3 or later (GPLv3+)
Classifier: Operating System :: OS Independent
Classifier: Programming Language :: Python :: 3.5
License-File: COPYING
Requires-Dist: papermill
Requires-Dist: luadata
